Metadata-Version: 2.1
Name: hbrs-grader
Version: 1.0
Summary: A jupyter workflow for grading exams
Home-page: UNKNOWN
Author: Jan Kleinert
Author-email: Jan.Kleinert@h-brs.de
License: To Do
Platform: UNKNOWN
